[{"id": 1, "name": "\u043a\u0430\u0440\u0430\u0441\u044c", "latin_name": "karas", "is_salt_water_fish": true, "sub_type_count": 1}, {"id": 2, "name": "\u043e\u043a\u0443\u043d\u044c", "latin_name": "okun", "is_salt_water_fish": false, "sub_type_count": 4}, {"id": 3, "name": "\u043f\u043b\u043e\u0442\u0432\u0430", "latin_name": "plotva", "is_salt_water_fish": true, "sub_type_count": 2}, {"id": 4, "name": "\u043a\u0430\u0440\u043f", "latin_name": "karp", "is_salt_water_fish": false, "sub_type_count": 9}, {"id": 5, "name": "\u0441\u043e\u043c", "latin_name": "som", "is_salt_water_fish": true, "sub_type_count": 0}]